tracking_log_model/__init__.py
tracking_log_model/tracking_log_model.py
tracking_log_model-1.0.0.dist-info/licenses/LICENSE.lic
tracking_log_model-1.0.0.dist-info/METADATA
tracking_log_model-1.0.0.dist-info/WHEEL
tracking_log_model-1.0.0.dist-info/top_level.txt
tracking_log_model-1.0.0.dist-info/RECORD
